[
  {
    "ContainingType": "ssh.authservice.Controllers.AuthController",
    "Method": "ChangePassword",
    "RelativePath": "api/Auth/change-password",
    "HttpMethod": "POST",
    "IsController": true,
    "Order": 0,
    "Parameters": [
      {
        "Name": "request",
        "Type": "ssh.authservice.DTOs.Request.ChangePasswordDTO",
        "IsRequired": true
      }
    ],
    "ReturnTypes": [
      {
        "Type": "ssh.authservice.DTOs.Common.ApiResponseDTO\u00601[[System.String, System.Private.CoreLib, Version=8.0.0.0, Culture=neutral, PublicKeyToken=7cec85d7bea7798e]]",
        "MediaTypes": [
          "text/plain",
          "application/json",
          "text/json"
        ],
        "StatusCode": 200
      }
    ]
  },
  {
    "ContainingType": "ssh.authservice.Controllers.AuthController",
    "Method": "Login",
    "RelativePath": "api/Auth/login",
    "HttpMethod": "POST",
    "IsController": true,
    "Order": 0,
    "Parameters": [
      {
        "Name": "request",
        "Type": "ssh.authservice.DTOs.Request.LoginRequestDTO",
        "IsRequired": true
      }
    ],
    "ReturnTypes": [
      {
        "Type": "ssh.authservice.DTOs.Common.ApiResponseDTO\u00601[[ssh.authservice.DTOs.Response.AuthResponseDTO, ssh.authservice, Version=1.0.0.0, Culture=neutral, PublicKeyToken=null]]",
        "MediaTypes": [
          "text/plain",
          "application/json",
          "text/json"
        ],
        "StatusCode": 200
      }
    ]
  },
  {
    "ContainingType": "ssh.authservice.Controllers.AuthController",
    "Method": "RefreshToken",
    "RelativePath": "api/Auth/refresh-token",
    "HttpMethod": "POST",
    "IsController": true,
    "Order": 0,
    "Parameters": [
      {
        "Name": "request",
        "Type": "ssh.authservice.DTOs.Response.TokenResponseDTO",
        "IsRequired": true
      }
    ],
    "ReturnTypes": [
      {
        "Type": "ssh.authservice.DTOs.Common.ApiResponseDTO\u00601[[ssh.authservice.DTOs.Response.TokenResponseDTO, ssh.authservice, Version=1.0.0.0, Culture=neutral, PublicKeyToken=null]]",
        "MediaTypes": [
          "text/plain",
          "application/json",
          "text/json"
        ],
        "StatusCode": 200
      }
    ]
  },
  {
    "ContainingType": "ssh.authservice.Controllers.AuthController",
    "Method": "Register",
    "RelativePath": "api/Auth/register",
    "HttpMethod": "POST",
    "IsController": true,
    "Order": 0,
    "Parameters": [
      {
        "Name": "request",
        "Type": "ssh.authservice.DTOs.Request.RegisterRequestDTO",
        "IsRequired": true
      }
    ],
    "ReturnTypes": [
      {
        "Type": "ssh.authservice.DTOs.Common.ApiResponseDTO\u00601[[ssh.authservice.DTOs.Response.AuthResponseDTO, ssh.authservice, Version=1.0.0.0, Culture=neutral, PublicKeyToken=null]]",
        "MediaTypes": [
          "text/plain",
          "application/json",
          "text/json"
        ],
        "StatusCode": 200
      }
    ]
  },
  {
    "ContainingType": "ssh.authservice.Controllers.DepartmentsController",
    "Method": "GetDepartments",
    "RelativePath": "api/Departments",
    "HttpMethod": "GET",
    "IsController": true,
    "Order": 0,
    "Parameters": [
      {
        "Name": "pageNumber",
        "Type": "System.Int32",
        "IsRequired": false
      },
      {
        "Name": "pageSize",
        "Type": "System.Int32",
        "IsRequired": false
      }
    ],
    "ReturnTypes": [
      {
        "Type": "ssh.authservice.DTOs.Common.ApiResponseDTO\u00601[[ssh.authservice.DTOs.Common.PagedResultDTO\u00601[[ssh.authservice.DTOs.Response.DepartmentResponseDTO, ssh.authservice, Version=1.0.0.0, Culture=neutral, PublicKeyToken=null]], ssh.authservice, Version=1.0.0.0, Culture=neutral, PublicKeyToken=null]]",
        "MediaTypes": [
          "text/plain",
          "application/json",
          "text/json"
        ],
        "StatusCode": 200
      }
    ]
  },
  {
    "ContainingType": "ssh.authservice.Controllers.DepartmentsController",
    "Method": "CreateDepartment",
    "RelativePath": "api/Departments",
    "HttpMethod": "POST",
    "IsController": true,
    "Order": 0,
    "Parameters": [
      {
        "Name": "request",
        "Type": "ssh.authservice.DTOs.Request.CreateDepartmentDTO",
        "IsRequired": true
      }
    ],
    "ReturnTypes": [
      {
        "Type": "ssh.authservice.DTOs.Common.ApiResponseDTO\u00601[[ssh.authservice.DTOs.Response.DepartmentResponseDTO, ssh.authservice, Version=1.0.0.0, Culture=neutral, PublicKeyToken=null]]",
        "MediaTypes": [
          "text/plain",
          "application/json",
          "text/json"
        ],
        "StatusCode": 200
      }
    ]
  },
  {
    "ContainingType": "ssh.authservice.Controllers.DepartmentsController",
    "Method": "GetDepartmentById",
    "RelativePath": "api/Departments/{id}",
    "HttpMethod": "GET",
    "IsController": true,
    "Order": 0,
    "Parameters": [
      {
        "Name": "id",
        "Type": "System.String",
        "IsRequired": true
      }
    ],
    "ReturnTypes": [
      {
        "Type": "ssh.authservice.DTOs.Common.ApiResponseDTO\u00601[[ssh.authservice.DTOs.Response.DepartmentResponseDTO, ssh.authservice, Version=1.0.0.0, Culture=neutral, PublicKeyToken=null]]",
        "MediaTypes": [
          "text/plain",
          "application/json",
          "text/json"
        ],
        "StatusCode": 200
      }
    ]
  },
  {
    "ContainingType": "ssh.authservice.Controllers.DepartmentsController",
    "Method": "UpdateDepartment",
    "RelativePath": "api/Departments/{id}",
    "HttpMethod": "PUT",
    "IsController": true,
    "Order": 0,
    "Parameters": [
      {
        "Name": "id",
        "Type": "System.String",
        "IsRequired": true
      },
      {
        "Name": "request",
        "Type": "ssh.authservice.DTOs.Request.CreateDepartmentDTO",
        "IsRequired": true
      }
    ],
    "ReturnTypes": [
      {
        "Type": "ssh.authservice.DTOs.Common.ApiResponseDTO\u00601[[ssh.authservice.DTOs.Response.DepartmentResponseDTO, ssh.authservice, Version=1.0.0.0, Culture=neutral, PublicKeyToken=null]]",
        "MediaTypes": [
          "text/plain",
          "application/json",
          "text/json"
        ],
        "StatusCode": 200
      }
    ]
  },
  {
    "ContainingType": "ssh.authservice.Controllers.DepartmentsController",
    "Method": "DeleteDepartment",
    "RelativePath": "api/Departments/{id}",
    "HttpMethod": "DELETE",
    "IsController": true,
    "Order": 0,
    "Parameters": [
      {
        "Name": "id",
        "Type": "System.String",
        "IsRequired": true
      }
    ],
    "ReturnTypes": [
      {
        "Type": "ssh.authservice.DTOs.Common.ApiResponseDTO\u00601[[System.String, System.Private.CoreLib, Version=8.0.0.0, Culture=neutral, PublicKeyToken=7cec85d7bea7798e]]",
        "MediaTypes": [
          "text/plain",
          "application/json",
          "text/json"
        ],
        "StatusCode": 200
      }
    ]
  },
  {
    "ContainingType": "ssh.authservice.Controllers.DepartmentsController",
    "Method": "GetDepartmentStatistics",
    "RelativePath": "api/Departments/{id}/statistics",
    "HttpMethod": "GET",
    "IsController": true,
    "Order": 0,
    "Parameters": [
      {
        "Name": "id",
        "Type": "System.String",
        "IsRequired": true
      }
    ],
    "ReturnTypes": [
      {
        "Type": "ssh.authservice.DTOs.Common.ApiResponseDTO\u00601[[ssh.authservice.DTOs.Response.DepartmentResponseDTO, ssh.authservice, Version=1.0.0.0, Culture=neutral, PublicKeyToken=null]]",
        "MediaTypes": [
          "text/plain",
          "application/json",
          "text/json"
        ],
        "StatusCode": 200
      }
    ]
  },
  {
    "ContainingType": "ssh.authservice.Controllers.RolesController",
    "Method": "GetRoles",
    "RelativePath": "api/Roles",
    "HttpMethod": "GET",
    "IsController": true,
    "Order": 0,
    "Parameters": [
      {
        "Name": "pageNumber",
        "Type": "System.Int32",
        "IsRequired": false
      },
      {
        "Name": "pageSize",
        "Type": "System.Int32",
        "IsRequired": false
      }
    ],
    "ReturnTypes": [
      {
        "Type": "ssh.authservice.DTOs.Common.ApiResponseDTO\u00601[[ssh.authservice.DTOs.Common.PagedResultDTO\u00601[[ssh.authservice.DTOs.Response.RoleResponseDTO, ssh.authservice, Version=1.0.0.0, Culture=neutral, PublicKeyToken=null]], ssh.authservice, Version=1.0.0.0, Culture=neutral, PublicKeyToken=null]]",
        "MediaTypes": [
          "text/plain",
          "application/json",
          "text/json"
        ],
        "StatusCode": 200
      }
    ]
  },
  {
    "ContainingType": "ssh.authservice.Controllers.RolesController",
    "Method": "CreateRole",
    "RelativePath": "api/Roles",
    "HttpMethod": "POST",
    "IsController": true,
    "Order": 0,
    "Parameters": [
      {
        "Name": "request",
        "Type": "ssh.authservice.DTOs.Response.RoleResponseDTO",
        "IsRequired": true
      }
    ],
    "ReturnTypes": [
      {
        "Type": "ssh.authservice.DTOs.Common.ApiResponseDTO\u00601[[ssh.authservice.DTOs.Response.RoleResponseDTO, ssh.authservice, Version=1.0.0.0, Culture=neutral, PublicKeyToken=null]]",
        "MediaTypes": [
          "text/plain",
          "application/json",
          "text/json"
        ],
        "StatusCode": 200
      }
    ]
  },
  {
    "ContainingType": "ssh.authservice.Controllers.RolesController",
    "Method": "GetRoleById",
    "RelativePath": "api/Roles/{id}",
    "HttpMethod": "GET",
    "IsController": true,
    "Order": 0,
    "Parameters": [
      {
        "Name": "id",
        "Type": "System.String",
        "IsRequired": true
      }
    ],
    "ReturnTypes": [
      {
        "Type": "ssh.authservice.DTOs.Common.ApiResponseDTO\u00601[[ssh.authservice.DTOs.Response.RoleResponseDTO, ssh.authservice, Version=1.0.0.0, Culture=neutral, PublicKeyToken=null]]",
        "MediaTypes": [
          "text/plain",
          "application/json",
          "text/json"
        ],
        "StatusCode": 200
      }
    ]
  },
  {
    "ContainingType": "ssh.authservice.Controllers.RolesController",
    "Method": "UpdateRole",
    "RelativePath": "api/Roles/{id}",
    "HttpMethod": "PUT",
    "IsController": true,
    "Order": 0,
    "Parameters": [
      {
        "Name": "id",
        "Type": "System.String",
        "IsRequired": true
      },
      {
        "Name": "request",
        "Type": "ssh.authservice.DTOs.Response.RoleResponseDTO",
        "IsRequired": true
      }
    ],
    "ReturnTypes": [
      {
        "Type": "ssh.authservice.DTOs.Common.ApiResponseDTO\u00601[[ssh.authservice.DTOs.Response.RoleResponseDTO, ssh.authservice, Version=1.0.0.0, Culture=neutral, PublicKeyToken=null]]",
        "MediaTypes": [
          "text/plain",
          "application/json",
          "text/json"
        ],
        "StatusCode": 200
      }
    ]
  },
  {
    "ContainingType": "ssh.authservice.Controllers.RolesController",
    "Method": "DeleteRole",
    "RelativePath": "api/Roles/{id}",
    "HttpMethod": "DELETE",
    "IsController": true,
    "Order": 0,
    "Parameters": [
      {
        "Name": "id",
        "Type": "System.String",
        "IsRequired": true
      }
    ],
    "ReturnTypes": [
      {
        "Type": "ssh.authservice.DTOs.Common.ApiResponseDTO\u00601[[System.String, System.Private.CoreLib, Version=8.0.0.0, Culture=neutral, PublicKeyToken=7cec85d7bea7798e]]",
        "MediaTypes": [
          "text/plain",
          "application/json",
          "text/json"
        ],
        "StatusCode": 200
      }
    ]
  },
  {
    "ContainingType": "ssh.authservice.Controllers.RolesController",
    "Method": "AssignRoleToUser",
    "RelativePath": "api/Roles/assign",
    "HttpMethod": "POST",
    "IsController": true,
    "Order": 0,
    "Parameters": [
      {
        "Name": "request",
        "Type": "ssh.authservice.DTOs.Request.AssignRoleDTO",
        "IsRequired": true
      }
    ],
    "ReturnTypes": [
      {
        "Type": "ssh.authservice.DTOs.Common.ApiResponseDTO\u00601[[System.String, System.Private.CoreLib, Version=8.0.0.0, Culture=neutral, PublicKeyToken=7cec85d7bea7798e]]",
        "MediaTypes": [
          "text/plain",
          "application/json",
          "text/json"
        ],
        "StatusCode": 200
      }
    ]
  },
  {
    "ContainingType": "ssh.authservice.Controllers.UsersController",
    "Method": "GetUsers",
    "RelativePath": "api/Users",
    "HttpMethod": "GET",
    "IsController": true,
    "Order": 0,
    "Parameters": [
      {
        "Name": "pageNumber",
        "Type": "System.Int32",
        "IsRequired": false
      },
      {
        "Name": "pageSize",
        "Type": "System.Int32",
        "IsRequired": false
      }
    ],
    "ReturnTypes": [
      {
        "Type": "ssh.authservice.DTOs.Common.ApiResponseDTO\u00601[[ssh.authservice.DTOs.Common.PagedResultDTO\u00601[[ssh.authservice.DTOs.Response.UserResponseDTO, ssh.authservice, Version=1.0.0.0, Culture=neutral, PublicKeyToken=null]], ssh.authservice, Version=1.0.0.0, Culture=neutral, PublicKeyToken=null]]",
        "MediaTypes": [
          "text/plain",
          "application/json",
          "text/json"
        ],
        "StatusCode": 200
      }
    ]
  },
  {
    "ContainingType": "ssh.authservice.Controllers.UsersController",
    "Method": "GetUserById",
    "RelativePath": "api/Users/{id}",
    "HttpMethod": "GET",
    "IsController": true,
    "Order": 0,
    "Parameters": [
      {
        "Name": "id",
        "Type": "System.String",
        "IsRequired": true
      }
    ],
    "ReturnTypes": [
      {
        "Type": "ssh.authservice.DTOs.Common.ApiResponseDTO\u00601[[ssh.authservice.DTOs.Response.UserResponseDTO, ssh.authservice, Version=1.0.0.0, Culture=neutral, PublicKeyToken=null]]",
        "MediaTypes": [
          "text/plain",
          "application/json",
          "text/json"
        ],
        "StatusCode": 200
      }
    ]
  },
  {
    "ContainingType": "ssh.authservice.Controllers.UsersController",
    "Method": "UpdateUser",
    "RelativePath": "api/Users/{id}",
    "HttpMethod": "PUT",
    "IsController": true,
    "Order": 0,
    "Parameters": [
      {
        "Name": "id",
        "Type": "System.String",
        "IsRequired": true
      },
      {
        "Name": "request",
        "Type": "ssh.authservice.DTOs.Request.UpdateUserDTO",
        "IsRequired": true
      }
    ],
    "ReturnTypes": [
      {
        "Type": "ssh.authservice.DTOs.Common.ApiResponseDTO\u00601[[ssh.authservice.DTOs.Response.UserResponseDTO, ssh.authservice, Version=1.0.0.0, Culture=neutral, PublicKeyToken=null]]",
        "MediaTypes": [
          "text/plain",
          "application/json",
          "text/json"
        ],
        "StatusCode": 200
      }
    ]
  },
  {
    "ContainingType": "ssh.authservice.Controllers.UsersController",
    "Method": "DeactivateUser",
    "RelativePath": "api/Users/{id}",
    "HttpMethod": "DELETE",
    "IsController": true,
    "Order": 0,
    "Parameters": [
      {
        "Name": "id",
        "Type": "System.String",
        "IsRequired": true
      }
    ],
    "ReturnTypes": [
      {
        "Type": "ssh.authservice.DTOs.Common.ApiResponseDTO\u00601[[System.String, System.Private.CoreLib, Version=8.0.0.0, Culture=neutral, PublicKeyToken=7cec85d7bea7798e]]",
        "MediaTypes": [
          "text/plain",
          "application/json",
          "text/json"
        ],
        "StatusCode": 200
      }
    ]
  },
  {
    "ContainingType": "ssh.authservice.Controllers.UsersController",
    "Method": "GetUsersByDepartment",
    "RelativePath": "api/Users/department/{departmentId}",
    "HttpMethod": "GET",
    "IsController": true,
    "Order": 0,
    "Parameters": [
      {
        "Name": "departmentId",
        "Type": "System.String",
        "IsRequired": true
      },
      {
        "Name": "pageNumber",
        "Type": "System.Int32",
        "IsRequired": false
      },
      {
        "Name": "pageSize",
        "Type": "System.Int32",
        "IsRequired": false
      }
    ],
    "ReturnTypes": [
      {
        "Type": "ssh.authservice.DTOs.Common.ApiResponseDTO\u00601[[ssh.authservice.DTOs.Common.PagedResultDTO\u00601[[ssh.authservice.DTOs.Response.UserResponseDTO, ssh.authservice, Version=1.0.0.0, Culture=neutral, PublicKeyToken=null]], ssh.authservice, Version=1.0.0.0, Culture=neutral, PublicKeyToken=null]]",
        "MediaTypes": [
          "text/plain",
          "application/json",
          "text/json"
        ],
        "StatusCode": 200
      }
    ]
  }
]